pythonvideoannotator_module_smoothpaths/__init__.py
pythonvideoannotator_module_smoothpaths/module.py
pythonvideoannotator_module_smoothpaths/smoothpaths_window.py
Python_video_annotator_module_smooth_paths-0.5.19.dist-info/METADATA
Python_video_annotator_module_smooth_paths-0.5.19.dist-info/WHEEL
Python_video_annotator_module_smooth_paths-0.5.19.dist-info/top_level.txt
Python_video_annotator_module_smooth_paths-0.5.19.dist-info/RECORD
