Metadata-Version: 2.1
Name: Python-video-annotator-module-smooth-paths
Version: 0.5.19
Summary: UNKNOWN
Home-page: https://bitbucket.org/fchampalimaud/pythonvideoannotator-module-smoothpaths
Author: ['Ricardo Ribeiro']
Author-email: ricardojvr@gmail.com
License: UNKNOWN
Platform: UNKNOWN
